yop/__init__.py
yop/cli.py
yop/types.py
yop/utils.py
yop-0.0.2.dist-info/LICENSE.md
yop-0.0.2.dist-info/METADATA
yop-0.0.2.dist-info/WHEEL
yop-0.0.2.dist-info/entry_points.txt
yop-0.0.2.dist-info/RECORD
