Metadata-Version: 2.1
Name: yop
Version: 0.0.2
Summary: Yubikey OTP Provisioner
License: Unlicense
Author: Andrii Yurchuk
Author-email: ay@mntw.re
Requires-Python: >=3.8.1,<4.0.0
Classifier: License :: OSI Approved
Classifier: Programming Language :: Python :: 3
Classifier: Programming Language :: Python :: 3.9
Classifier: Programming Language :: Python :: 3.10
Classifier: Programming Language :: Python :: 3.11
Classifier: Programming Language :: Python :: 3.12
Requires-Dist: click (>=8.1.7,<9.0.0)
Requires-Dist: tabulate (>=0.9.0,<0.10.0)
Requires-Dist: yubikey-manager (>=5.3.0,<6.0.0)
